pydataspace/__init__.py
pydataspace/data/jsonLDObject.yaml
pydataspace/jsonLDObject/__init__.py
pydataspace/jsonLDObject/context.py
pydataspace/jsonLDObject/jsonLDObject.py
pydataspace/jsonLDObject/objectDependencies.py
pydataspace_jsonLDObject-0.0.0.13.dist-info/METADATA
pydataspace_jsonLDObject-0.0.0.13.dist-info/WHEEL
pydataspace_jsonLDObject-0.0.0.13.dist-info/top_level.txt
pydataspace_jsonLDObject-0.0.0.13.dist-info/RECORD
