Metadata-Version: 2.1
Name: pydataspace-jsonLDObject
Version: 0.0.0.13
Summary: Objet FederatedIdentifier pour pydataspace
Home-page: https://gitlab.com/dataspace2/ontologies/jsonldobject
Author: Olivier Tirat
Author-email: olivier.tirat@free.fr
License: UNKNOWN
Platform: UNKNOWN
Classifier: Programming Language :: Python :: 3
Classifier: License :: OSI Approved :: MIT License
Classifier: Operating System :: OS Independent
Requires-Python: >=3.6
